README.md
setup.py
shhh/__init__.py
shhh/boolean.py
shhh/byteseq.py
shhh/dictionary.py
shhh/float.py
shhh/integer.py
shhh/item.py
shhh/list.py
shhh/string.py
shhh/token.py
shhh/util.py
shhh.egg-info/PKG-INFO
shhh.egg-info/SOURCES.txt
shhh.egg-info/dependency_links.txt
shhh.egg-info/requires.txt
shhh.egg-info/top_level.txt
test/test.py