Metadata-Version: 2.1
Name: shhh
Version: 0.1.0
Summary: Structured HTTP Headers (handily)
Home-page: http://github.com/mnot/shhh/
Author: Mark Nottingham
Author-email: mnot@mnot.net
License: MIT
Download-URL: http://github.com/mnot/thor/tarball/shhh-0.1.0
Platform: UNKNOWN
Classifier: Development Status :: 4 - Beta
Classifier: Intended Audience :: Developers
Classifier: License :: OSI Approved :: MIT License
Classifier: Programming Language :: Python
Classifier: Programming Language :: Python :: 3.5
Classifier: Operating System :: POSIX
Classifier: Topic :: Internet :: WWW/HTTP
Classifier: Topic :: Software Development :: Libraries :: Python Modules
Provides: shhh
Requires-Python: >=3.5
Provides-Extra: dev
